tinycomp/__init__.py
tinycomp/api_manager.py
tinycomp/cli.py
tinycomp/compressor.py
tinycomp/tests/__init__.py
tinycomp/tests/test_compressor.py
tinycomp_amadeus-0.1.5.dist-info/LICENSE
tinycomp_amadeus-0.1.5.dist-info/METADATA
tinycomp_amadeus-0.1.5.dist-info/WHEEL
tinycomp_amadeus-0.1.5.dist-info/entry_points.txt
tinycomp_amadeus-0.1.5.dist-info/top_level.txt
tinycomp_amadeus-0.1.5.dist-info/RECORD
