Metadata-Version: 2.1
Name: tinycomp-amadeus
Version: 0.1.5
Summary: A Python package for compressing images using TinyPNG API
Home-page: https://github.com/Amadeus9029/tinycomp
Author: Amadeus9029
Author-email: 965720890@qq.com
Classifier: Development Status :: 3 - Alpha
Classifier: Intended Audience :: Developers
Classifier: License :: OSI Approved :: MIT License
Classifier: Operating System :: OS Independent
Classifier: Programming Language :: Python :: 3
Classifier: Programming Language :: Python :: 3.6
Classifier: Programming Language :: Python :: 3.7
Classifier: Programming Language :: Python :: 3.8
Classifier: Programming Language :: Python :: 3.9
Requires-Python: >=3.6
License-File: LICENSE
Requires-Dist: tinify
Requires-Dist: requests
Requires-Dist: tqdm
Requires-Dist: beautifulsoup4
Requires-Dist: selenium
Requires-Dist: fake-useragent
